{
  "brand_id": "brand_airbnb-com_d0f300dd",
  "official_domain": "airbnb.com",
  "crawled_page_count": 1,
  "unresolved": false,
  "titles": [
    "Airbnb: Vacation Rentals, Cabins, Beach Houses, Unique Homes &amp; Experiences"
  ],
  "descriptions": [
    "Get an Airbnb for every kind of trip → 8 million vacation rentals → 2 million Guest Favorites → 220+ countries and regions worldwide"
  ],
  "keywords": [
    "airbnb",
    "vacation",
    "rentals",
    "cabins",
    "beach",
    "houses",
    "unique",
    "homes",
    "experiences",
    "homepage",
    "every",
    "kind",
    "trip",
    "million",
    "guest",
    "favorites",
    "countries",
    "regions",
    "worldwide",
    "skip",
    "content",
    "sorry",
    "some",
    "parts"
  ],
  "price_hints": [],
  "landing_pages": [
    "https://airbnb.com/"
  ],
  "updated_at": "2026-02-21T12:37:52.721Z"
}
