{
  "brand_id": "brand_wpguardian-com_9596186c",
  "official_domain": "wpguardian.com",
  "crawled_page_count": 1,
  "unresolved": false,
  "titles": [
    "Effective Security for WordPress Sites- WPGuardian"
  ],
  "descriptions": [
    "Your All Seeing Eye to proactively scan &amp; identify threats"
  ],
  "keywords": [
    "effective",
    "security",
    "wordpress",
    "sites",
    "wpguardian",
    "your",
    "seeing",
    "proactively",
    "scan",
    "identify",
    "threats",
    "benefits",
    "features",
    "solutions",
    "pricing",
    "login",
    "flexible",
    "update"
  ],
  "price_hints": [
    "$5",
    "$15",
    "$3"
  ],
  "landing_pages": [
    "https://wpguardian.com/"
  ],
  "updated_at": "2026-02-21T12:38:05.378Z"
}
